latexpages/__init__.py
latexpages/__main__.py
latexpages/backend.py
latexpages/building.py
latexpages/cleaning.py
latexpages/jobs.py
latexpages/numbering.py
latexpages/pdfpages.py
latexpages/settings.ini
latexpages/template.tex
latexpages/tools.py
latexpages-0.8.dist-info/licenses/LICENSE.txt
latexpages-0.8.dist-info/METADATA
latexpages-0.8.dist-info/WHEEL
latexpages-0.8.dist-info/entry_points.txt
latexpages-0.8.dist-info/top_level.txt
latexpages-0.8.dist-info/RECORD
