Metadata-Version: 2.4
Name: latexpages
Version: 0.8
Summary: Combine LaTeX docs into a single PDF
Author-email: Sebastian Bank <sebastian.bank@uni-leipzig.de>
License-Expression: MIT
Project-URL: Homepage, https://github.com/xflr6/latexpages
Project-URL: Issue Tracker, https://github.com/xflr6/latexpages/issues
Project-URL: CI, https://github.com/xflr6/latexpages/actions
Keywords: pdfpages,parallel,compilation,proceedings
Platform: any
Classifier: Development Status :: 4 - Beta
Classifier: Environment :: Console
Classifier: Intended Audience :: End Users/Desktop
Classifier: Intended Audience :: Science/Research
Classifier: Operating System :: OS Independent
Classifier: Programming Language :: Python :: 3
Classifier: Programming Language :: Python :: 3.10
Classifier: Programming Language :: Python :: 3.11
Classifier: Programming Language :: Python :: 3.12
Classifier: Programming Language :: Python :: 3.13
Classifier: Programming Language :: Python :: 3.14
Classifier: Topic :: Printing
Classifier: Topic :: Text Processing :: Markup :: LaTeX
Requires-Python: >=3.10
License-File: LICENSE.txt
Provides-Extra: dev
Requires-Dist: build; extra == "dev"
Requires-Dist: wheel; extra == "dev"
Requires-Dist: twine; extra == "dev"
Requires-Dist: mypy; extra == "dev"
Requires-Dist: flake8; extra == "dev"
Requires-Dist: Flake8-pyproject; extra == "dev"
Requires-Dist: pep8-naming; extra == "dev"
Provides-Extra: test
Requires-Dist: coverage[toml]; extra == "test"
Dynamic: license-file
